berryinfo/__init__.py
berryinfo/berryinfo.py
berryinfo/ssdp.py
berryinfo-1.0.0.dist-info/LICENSE
berryinfo-1.0.0.dist-info/METADATA
berryinfo-1.0.0.dist-info/WHEEL
berryinfo-1.0.0.dist-info/entry_points.txt
berryinfo-1.0.0.dist-info/top_level.txt
berryinfo-1.0.0.dist-info/RECORD
