Metadata-Version: 2.1
Name: berryinfo
Version: 1.0.0
Summary: berryinfo makes obtaining diagnostic information about your device easy!
Home-page: https://codedin.wales/picymru/berryinfo
Author: PiCymru
Author-email: code@picymru.email
License: MIT
Platform: linux
Classifier: Development Status :: 4 - Beta
Classifier: Environment :: Console
Classifier: Intended Audience :: Developers
Classifier: License :: OSI Approved :: MIT License
Classifier: Programming Language :: Python :: 2
Classifier: Programming Language :: Python :: 3
Requires-Dist: bottle
Requires-Dist: tornado
